nightwatch/__init__.py
nightwatch/config.py
nightwatch/logging.py
nightwatch/bot/__init__.py
nightwatch/bot/client.py
nightwatch/bot/types.py
nightwatch/client/__init__.py
nightwatch/client/__main__.py
nightwatch/client/extra/__init__.py
nightwatch/client/extra/select.py
nightwatch/client/extra/ui.py
nightwatch/client/extra/wswrap.py
nightwatch/client/extra/commands/__init__.py
nightwatch/client/vendor/scroll.py
nightwatch/client/vendor/iipython/__init__.py
nightwatch/client/vendor/iipython/term.py
nightwatch/client/vendor/iipython/iikp/__init__.py
nightwatch/client/vendor/iipython/iikp/keys.py
nightwatch/client/vendor/iipython/iikp/read.py
nightwatch/client/vendor/iipython/iikp/read_linux.py
nightwatch/rics/__init__.py
nightwatch/rics/routing/files.py
nightwatch/rics/routing/image_forward.py
nightwatch/web/index.html
nightwatch/web/audio/notification.mp3
nightwatch/web/css/main.css
nightwatch/web/fonts/fira.woff2
nightwatch/web/fonts/fira_mono.woff2
nightwatch/web/images/favicon-alt.png
nightwatch/web/images/favicon.png
nightwatch/web/js/nightwatch.js
nightwatch/web/js/flows/connection.js
nightwatch/web/js/flows/files.js
nightwatch/web/js/flows/welcome.js
nightwatch_chat-0.11.3.dist-info/METADATA
nightwatch_chat-0.11.3.dist-info/WHEEL
nightwatch_chat-0.11.3.dist-info/entry_points.txt
nightwatch_chat-0.11.3.dist-info/licenses/LICENSE.txt
nightwatch_chat-0.11.3.dist-info/RECORD
