Metadata-Version: 2.3
Name: nightwatch-chat
Version: 0.11.3
Summary: The chatting application to end all chatting applications.
Project-URL: Homepage, https://github.com/iiPythonx/nightwatch
Project-URL: Issues, https://github.com/iiPythonx/nightwatch/issues
Author-email: iiPython <ben@iipython.dev>
Classifier: License :: OSI Approved :: MIT License
Classifier: Operating System :: OS Independent
Classifier: Programming Language :: Python :: 3
Requires-Python: >=3.10
Requires-Dist: emoji>=2.14.0
Requires-Dist: nanoid>=2.0.0
Requires-Dist: orjson>=3.10.11
Requires-Dist: readchar>=4.2.1
Requires-Dist: requests>=2.32.3
Requires-Dist: urwid>=2.6.16
Requires-Dist: websockets>=14.1
Provides-Extra: serve
Requires-Dist: fastapi>=0.115.5; extra == 'serve'
Requires-Dist: pydantic>=2.9.2; extra == 'serve'
Requires-Dist: python-multipart>=0.0.17; extra == 'serve'
Requires-Dist: uvicorn[standard]>=0.32.1; extra == 'serve'
